mkdocs_izsam_video/__init__.py
mkdocs_izsam_video/plugin.py
mkdocs_izsam_video-1.0.3.dist-info/LICENSE.txt
mkdocs_izsam_video-1.0.3.dist-info/METADATA
mkdocs_izsam_video-1.0.3.dist-info/WHEEL
mkdocs_izsam_video-1.0.3.dist-info/entry_points.txt
mkdocs_izsam_video-1.0.3.dist-info/top_level.txt
mkdocs_izsam_video-1.0.3.dist-info/RECORD
