Metadata-Version: 2.1
Name: mkdocs-izsam-video
Version: 1.0.3
Summary: MkDocs plugin to insert videos in documentation.
Home-page: UNKNOWN
Author: Alessandro De Luca
Author-email: al.deluca@izs.it
License: MIT
Keywords: MkDocs,Video,HTML5 video tag
Platform: UNKNOWN
Requires-Python: >=3.8
License-File: LICENSE.txt
Requires-Dist: mkdocs (>=1.0.4)
